eve_auth_jwt/__init__.py
eve_auth_jwt/auth.py
eve_auth_jwt/verify_token.py
eve_auth_jwt_fork-1.2.2.dist-info/DESCRIPTION.rst
eve_auth_jwt_fork-1.2.2.dist-info/METADATA
eve_auth_jwt_fork-1.2.2.dist-info/RECORD
eve_auth_jwt_fork-1.2.2.dist-info/WHEEL
eve_auth_jwt_fork-1.2.2.dist-info/metadata.json
eve_auth_jwt_fork-1.2.2.dist-info/top_level.txt
