Metadata-Version: 2.0
Name: eve-auth-jwt-fork
Version: 1.2.2
Summary: Eve JWT authentication, rs/eve-auth-jwt's fork.
Home-page: https://github.com/xdtianyu/eve-auth-jwt
Author: Olivier Poitrey
Author-email: rs@dailymotion.com
License: MIT
Keywords: eve,api,rest,oauth,auth,jwt
Platform: UNKNOWN
Classifier: Development Status :: 4 - Beta
Classifier: Environment :: Web Environment
Classifier: Environment :: No Input/Output (Daemon)
Classifier: Intended Audience :: Developers
Classifier: Intended Audience :: Telecommunications Industry
Classifier: License :: OSI Approved :: MIT License
Classifier: Operating System :: Unix
Classifier: Programming Language :: Python
Classifier: Programming Language :: Python :: 2.7
Classifier: Programming Language :: Python :: 3.4
Classifier: Topic :: Internet :: WWW/HTTP
Classifier: Topic :: Internet :: WWW/HTTP :: HTTP Servers
Classifier: Topic :: Security
Requires-Dist: cryptography (>=2.5)
Requires-Dist: eve (>=0.7.5)
Requires-Dist: pyjwt (==1.7.1)
